sarpy_apps/__about__.py
sarpy_apps/__init__.py
sarpy_apps/apps/__init__.py
sarpy_apps/apps/annotation_tool.py
sarpy_apps/apps/aperture_tool.py
sarpy_apps/apps/cphd_validation_tool.py
sarpy_apps/apps/full_support_tool.py
sarpy_apps/apps/image_viewer.py
sarpy_apps/apps/local_support_tool.py
sarpy_apps/apps/pulse_explorer.py
sarpy_apps/apps/rcs_tool.py
sarpy_apps/apps/validation_tool.py
sarpy_apps/apps/wake_tool.py
sarpy_apps/apps/labeling_tool/__init__.py
sarpy_apps/apps/labeling_tool/labeling_tool.py
sarpy_apps/apps/labeling_tool/schema_editor.py
sarpy_apps/supporting_classes/__init__.py
sarpy_apps/supporting_classes/cphd_plotting.py
sarpy_apps/supporting_classes/file_filters.py
sarpy_apps/supporting_classes/image_reader.py
sarpy_apps/supporting_classes/metaviewer.py
sarpy_apps/supporting_classes/widget_with_metadata.py
sarpy_apps/supporting_classes/metaicon/__init__.py
sarpy_apps/supporting_classes/metaicon/metaicon.py
sarpy_apps/supporting_classes/metaicon/metaicon_data_container.py
sarpy_apps-1.1.25.dist-info/licenses/LICENSE
sarpy_apps-1.1.25.dist-info/METADATA
sarpy_apps-1.1.25.dist-info/WHEEL
sarpy_apps-1.1.25.dist-info/top_level.txt
sarpy_apps-1.1.25.dist-info/zip-safe
sarpy_apps-1.1.25.dist-info/RECORD
