Metadata-Version: 2.4
Name: sarpy_apps
Version: 1.1.25
Summary: This provides a set of GUI tools based on tkinter for visualizing and interacting with SAR imagery and related data.
Home-page: https://github.com/ngageoint/sarpy_apps
Author: National Geospatial-Intelligence Agency
Author-email: richard.m.naething@nga.mil
License: MIT
Platform: any
Classifier: Development Status :: 4 - Beta
Classifier: Intended Audience :: Developers
Classifier: License :: OSI Approved :: MIT License
Classifier: Programming Language :: Python :: 3.9
Classifier: Programming Language :: Python :: 3.10
Classifier: Programming Language :: Python :: 3.11
Classifier: Programming Language :: Python :: 3.12
Classifier: Programming Language :: Python :: 3.13
Classifier: Programming Language :: Python :: 3.14
License-File: LICENSE
Requires-Dist: numpy
Requires-Dist: matplotlib
Requires-Dist: Pillow
Requires-Dist: plotly
Requires-Dist: sarpy>=1.3.46
Requires-Dist: tk_builder>=1.1.12
Dynamic: author
Dynamic: author-email
Dynamic: classifier
Dynamic: description
Dynamic: description-content-type
Dynamic: home-page
Dynamic: license
Dynamic: license-file
Dynamic: platform
Dynamic: requires-dist
Dynamic: summary
